[
    {
        "productos": [
            {
                "nombre": "camiseta1",
                "descripcion": "Camiseta gráfico texto",
                "stock": 20,
                "precio": 7.99
                        
            },
            {
                "nombre": "camiseta2",
                "descripcion": "Camiseta mujeres ilustradas",
                "stock": 20,
                "precio": 12.99
            },
            {
                "nombre": "pantalon1",
                "descripcion": "Pantalón wide leg",
                "stock": 20,
                "precio": 19.99
            },
            {
                "nombre": "pantalon2",
                "descripcion": "Pantalón culotte vestir",
                "stock": 20,
                "precio": 29.99
            },
            {
                "nombre": "vestido1",
                "descripcion": "Vestido midi manga larga",
                "stock": 20,
                "precio": 19.99
            },
            {
                "nombre": "vestido2",
                "descripcion": "America vestido",
                "stock": 20,
                "precio": 35.99
            },
            {
                "nombre": "bolso1",
                "descripcion": "Bandolera piel fleco",
                "stock": 20,
                "precio": 39.99
            },
            {
                "nombre": "bolso2",
                "descripcion": "Bandolera cierra",
                "stock": 20,
                "precio": 12.99
            }
        ]
    },
    {
        "usuarios": [
            {
                "user": "root",
                "nombre": "Root root root",
                "email": "root@github.com"
            },
            {
                "user": "narroyoc",
                "nombre": "Noelia Arroyo Castaño",
                "email": "noelia@github.com"
            }
        ]
    },
    {
        "pedidos": [
            {
                "user": "root",
                "dirección": "Avenida España, 3",
                "tarjeta": "1234",
                "productos": [
                    "camiseta1 x2",
                    ""
                ]
            },
            {
                "user": "narroyoc",
                "dirección": "Calle Talavera, 5",
                "tarjeta": "5678",
                "productos": [
                    "",
                    "camiseta2 x4"
                ]
            }
        ]
    }
]